pyframework/__init__.py
pyframework/core/__init__.py
pyframework/core/exception/__init__.py
pyframework/core/exception/core_exception.py
pyframework/core/logging/__init__.py
pyframework/core/logging/logger.py
pyframework/core/server/__init__.py
pyframework/core/server/singleton_pyframework.py
pyframework/core/server/startup.py
pyframework/logicframework/__init__.py
pyframework/testframework/__init__.py
pyframework/util/__init__.py
pyframework/util/logger.py
pyframework/util/properties.py
pyframework/util/random.py
pyframework/util/session.py
pyframework/util/uuid.py
pyframework/util/cache/__init__.py
pyframework/util/cache/base_cache.py
pyframework/util/cache/cache_factory.py
pyframework/util/cache/impl/__init__.py
pyframework/util/cache/impl/redis_cache.py
pyframework/util/cache/impl/sqlite_cache.py
pyframework/util/concurrent/__init__.py
pyframework/util/concurrent/atomic.py
pyframework/util/datetime/__init__.py
pyframework/util/datetime/date.py
pyframework/util/datetime/time.py
pyframework/util/datetime/timestamp.py
pyframework/util/datetime/timezone.py
pyframework/util/io/__init__.py
pyframework/util/io/file/__init__.py
pyframework/util/io/file/zip.py
pyframework/util/io/path/__init__.py
pyframework/util/io/path/sys.py
pyframework/util/numeric/__init__.py
pyframework/util/numeric/cast/__init__.py
pyframework/util/numeric/math/__init__.py
pyframework/util/string/__init__.py
pyframework/util/string/cast/__init__.py
pyframework/util/string/check/__init__.py
pyframework/util/string/serialization/__init__.py
pyframework/util/string/serialization/json.py
pyframework/util/system/__init__.py
pyframework/util/type/__init__.py
pyframework/util/type/check/__init__.py
pyframework/webframework/__init__.py
pyframework/webframework/controller/__init__.py
pyframework/webframework/data/__init__.py
pyframework/webframework/data/response.py
pyframework/webframework/exception/__init__.py
pythonframework-0.2.0.dist-info/DESCRIPTION.rst
pythonframework-0.2.0.dist-info/METADATA
pythonframework-0.2.0.dist-info/RECORD
pythonframework-0.2.0.dist-info/WHEEL
pythonframework-0.2.0.dist-info/metadata.json
pythonframework-0.2.0.dist-info/top_level.txt
