Metadata-Version: 1.0
Name: pythonframework
Version: 0.2.0
Summary: pyframework powerd by lanceyan.com
Home-page: https://github.com/lanceyan/pyframework
Author: lanceyan
Author-email: lanceyan@vip.qq.com
License: MIT License
Keywords: pythonframework
Platform: UNKNOWN
